CHANGELOG.md
LICENSE
MANIFEST.in
README.md
setup.cfg
setup.py
TracChangeFileBiffPlugin.egg-info/PKG-INFO
TracChangeFileBiffPlugin.egg-info/SOURCES.txt
TracChangeFileBiffPlugin.egg-info/dependency_links.txt
TracChangeFileBiffPlugin.egg-info/entry_points.txt
TracChangeFileBiffPlugin.egg-info/requires.txt
TracChangeFileBiffPlugin.egg-info/top_level.txt
changefilebiff/__init__.py
changefilebiff/admin.py
changefilebiff/api.py
changefilebiff/matcher.py
changefilebiff/model.py
changefilebiff/locale/messages.pot
changefilebiff/locale/ja/LC_MESSAGES/changefilebiff.mo
changefilebiff/locale/ja/LC_MESSAGES/changefilebiff.po
changefilebiff/templates/changefilebiff_admin.html