Metadata-Version: 1.1
Name: TracChangeFileBiffPlugin
Version: 0.4.0
Summary: Provides a feature like Biff for file in repository
Home-page: http://trac-hacks.org/wiki/TracChangeFileBiffPlugin
Author: Tetsuya Morimoto
Author-email: tetsuya dot morimoto at gmail dot com
License: Apache License 2.0
Keywords: trac,plugin,ticket,changeset,biff
Platform: UNKNOWN
Classifier: Framework :: Trac
Classifier: Development Status :: 4 - Beta
Classifier: Environment :: Web Environment
Classifier: License :: OSI Approved :: Apache Software License
Classifier: Intended Audience :: Developers
Classifier: Operating System :: OS Independent
Classifier: Programming Language :: Python
Classifier: Topic :: Software Development
